ippai/__init__.py
ippai-0.0.1.dist-info/LICENSE
ippai-0.0.1.dist-info/METADATA
ippai-0.0.1.dist-info/WHEEL
ippai-0.0.1.dist-info/top_level.txt
ippai-0.0.1.dist-info/RECORD
