Metadata-Version: 2.1
Name: ippai
Version: 0.0.1
Summary: Image Processing for Photoacoustic Imaging
Home-page: UNKNOWN
Author: Computer Assisted Medical Interventions, DKFZ
Author-email: UNKNOWN
License: UNKNOWN
Platform: UNKNOWN
Requires-Dist: numpy
